l20n/__init__.py
l20n/format/__init__.py
l20n/format/ast.py
l20n/format/parser.py
l20n/format/serializer.py
l20n-4.0.0a1.dist-info/DESCRIPTION.rst
l20n-4.0.0a1.dist-info/METADATA
l20n-4.0.0a1.dist-info/RECORD
l20n-4.0.0a1.dist-info/WHEEL
l20n-4.0.0a1.dist-info/metadata.json
l20n-4.0.0a1.dist-info/top_level.txt
