Metadata-Version: 2.0
Name: l20n
Version: 4.0.0a1
Summary: Python L20n library
Home-page: https://github.com/l20n/python-l20n
Author: Zibi Braniecki
Author-email: gandalf@mozilla.com
License: APL 2
Platform: UNKNOWN
Classifier: Development Status :: 3 - Alpha
Classifier: Intended Audience :: Developers
Classifier: License :: OSI Approved :: Apache Software License
Classifier: Programming Language :: Python :: 2.6
Classifier: Programming Language :: Python :: 2.7
Classifier: Programming Language :: Python :: 3.5
Requires-Dist: six
